{
  "title": "Бория",
  "shortDescription": "Фентъзи поредица: Бория",
  "genre": "fantasy",
  "books": [
    {
      "id": "the-healer-of-blackstone",
      "title": "Лечителят от Блекстоун",
      "epubFileName": "the-healer-of-blackstone_bg.epub",
      "price": 1.99,
      "genre": "fantasy",
      "is_latest": false
    },
    {
      "id": "the-guardian-of-briest",
      "title": "Пазителката на Бриест",
      "epubFileName": "the-guardian-of-briest_bg.epub",
      "price": 3.99,
      "genre": "fantasy",
      "is_latest": false
    },
    {
      "id": "two-worlds",
      "title": "Два свята",
      "epubFileName": "two-worlds_bg.epub",
      "price": 3.99,
      "genre": "fantasy",
      "is_latest": false
    }
  ]
}